subjectdb_manager/__init__.py
subjectdb_manager/subjectdb_manager.py
subjectdb_manager-0.1.2.dist-info/WHEEL
subjectdb_manager-0.1.2.dist-info/entry_points.txt
subjectdb_manager-0.1.2.dist-info/METADATA
subjectdb_manager-0.1.2.dist-info/RECORD
