Metadata-Version: 2.1
Name: subjectdb-manager
Version: 0.1.2
Summary: 
Author: Greg Schwimer
Author-email: schwim@bitrail.com
Requires-Python: >=3.9,<4.0
Classifier: Programming Language :: Python :: 3
Classifier: Programming Language :: Python :: 3.9
Classifier: Programming Language :: Python :: 3.10
Classifier: Programming Language :: Python :: 3.11
Requires-Dist: arrow (>=1.2.3,<2.0.0)
Requires-Dist: click (>=8.1.3,<9.0.0)
Requires-Dist: pyyaml (>=6.0,<7.0)
